{
  "data": {
    "article": {},
    "attachments": {},
    "author_id": "467659726",
    "conversation_id": "2073654249125495278",
    "created_at": "2026-07-05T06:24:34.000Z",
    "edit_controls": {
      "editable_until": "2026-07-05T07:24:34.000Z",
      "edits_remaining": 5,
      "is_edit_eligible": true
    },
    "edit_history_tweet_ids": [
      "2073654249125495278"
    ],
    "entities": {},
    "geo": {},
    "id": "2073654249125495278",
    "lang": "zh",
    "note_tweet": {
      "entities": {}
    },
    "possibly_sensitive": false,
    "public_metrics": {
      "bookmark_count": 0,
      "impression_count": 0,
      "like_count": 0,
      "quote_count": 0,
      "reply_count": 0,
      "retweet_count": 0
    },
    "reply_settings": "everyone",
    "text": "26年上半年用三个词概括🥺\n恐吓教育\n粉红大象效应\n权力表演"
  },
  "includes": {
    "tweets": [
      {
        "article": {},
        "attachments": {},
        "author_id": "467659726",
        "conversation_id": "2073654249125495278",
        "created_at": "2026-07-05T06:24:34.000Z",
        "edit_controls": {
          "editable_until": "2026-07-05T07:24:34.000Z",
          "edits_remaining": 5,
          "is_edit_eligible": true
        },
        "edit_history_tweet_ids": [
          "2073654249125495278"
        ],
        "entities": {},
        "geo": {},
        "id": "2073654249125495278",
        "lang": "zh",
        "note_tweet": {
          "entities": {}
        },
        "possibly_sensitive": false,
        "public_metrics": {
          "bookmark_count": 0,
          "impression_count": 0,
          "like_count": 0,
          "quote_count": 0,
          "reply_count": 0,
          "retweet_count": 0
        },
        "reply_settings": "everyone",
        "text": "26年上半年用三个词概括🥺\n恐吓教育\n粉红大象效应\n权力表演"
      }
    ],
    "users": [
      {
        "created_at": "2012-01-18T18:17:48.000Z",
        "description": "绝世大坏猫🐈‍⬛咬人也咬自己，咬完再挠一爪子🐾别靠太近，我会咬你也可能抱你。——坏猫不讲理，只会哈气",
        "id": "467659726",
        "location": "距离514米",
        "name": "坏猫",
        "profile_image_url": "https://pbs.twimg.com/profile_images/2046649877283901440/KYxuEqRD_normal.jpg",
        "protected": false,
        "public_metrics": {
          "followers_count": 3066,
          "following_count": 54,
          "like_count": 11457,
          "listed_count": 5,
          "media_count": 253,
          "tweet_count": 1630
        },
        "url": "",
        "username": "WorstCat",
        "verified": false
      }
    ]
  }
}