{
  "data": {
    "article": {},
    "attachments": {
      "media_keys": [
        "3_2048798176136871936"
      ]
    },
    "author_id": "467659726",
    "conversation_id": "2048636734435709384",
    "created_at": "2026-04-27T16:15:25.000Z",
    "edit_controls": {
      "editable_until": "2026-04-27T17:15:25.000Z",
      "edits_remaining": 5,
      "is_edit_eligible": false
    },
    "edit_history_tweet_ids": [
      "2048798179387457652"
    ],
    "entities": {
      "mentions": [
        {
          "end": 14,
          "id": "1403720942858035201",
          "start": 0,
          "username": "zhouzhouneko2"
        }
      ],
      "urls": [
        {
          "display_url": "pic.x.com/x1ECRS8wXp",
          "end": 79,
          "expanded_url": "https://x.com/WorstCat/status/2048798179387457652/photo/1",
          "media_key": "3_2048798176136871936",
          "start": 56,
          "url": "https://t.co/x1ECRS8wXp"
        }
      ]
    },
    "geo": {},
    "id": "2048798179387457652",
    "in_reply_to_user_id": "1403720942858035201",
    "lang": "zh",
    "note_tweet": {
      "entities": {}
    },
    "possibly_sensitive": false,
    "public_metrics": {
      "bookmark_count": 0,
      "impression_count": 0,
      "like_count": 0,
      "quote_count": 0,
      "reply_count": 0,
      "retweet_count": 0
    },
    "referenced_tweets": [
      {
        "id": "2048636734435709384",
        "type": "replied_to"
      }
    ],
    "reply_settings": "everyone",
    "text": "@zhouzhouneko2 成分太复杂啦性价比不如白兔，是厚生省认证的日本oder品鉴榜第七位ꉂ(ˊᗜˋ*) https://t.co/x1ECRS8wXp"
  },
  "includes": {
    "media": [
      {
        "height": 2084,
        "media_key": "3_2048798176136871936",
        "public_metrics": {},
        "type": "photo",
        "url": "https://pbs.twimg.com/media/HG7LFhEbQAAvXZH.jpg",
        "width": 1440
      },
      {
        "height": 1829,
        "media_key": "3_2048636730291671040",
        "public_metrics": {},
        "type": "photo",
        "url": "https://pbs.twimg.com/media/HG44QIbaUAAFHHl.jpg",
        "width": 1080
      }
    ],
    "tweets": [
      {
        "article": {},
        "attachments": {
          "media_keys": [
            "3_2048798176136871936"
          ]
        },
        "author_id": "467659726",
        "conversation_id": "2048636734435709384",
        "created_at": "2026-04-27T16:15:25.000Z",
        "edit_controls": {
          "editable_until": "2026-04-27T17:15:25.000Z",
          "edits_remaining": 5,
          "is_edit_eligible": false
        },
        "edit_history_tweet_ids": [
          "2048798179387457652"
        ],
        "entities": {
          "mentions": [
            {
              "end": 14,
              "id": "1403720942858035201",
              "start": 0,
              "username": "zhouzhouneko2"
            }
          ],
          "urls": [
            {
              "display_url": "pic.x.com/x1ECRS8wXp",
              "end": 79,
              "expanded_url": "https://x.com/WorstCat/status/2048798179387457652/photo/1",
              "media_key": "3_2048798176136871936",
              "start": 56,
              "url": "https://t.co/x1ECRS8wXp"
            }
          ]
        },
        "geo": {},
        "id": "2048798179387457652",
        "in_reply_to_user_id": "1403720942858035201",
        "lang": "zh",
        "note_tweet": {
          "entities": {}
        },
        "possibly_sensitive": false,
        "public_metrics": {
          "bookmark_count": 0,
          "impression_count": 0,
          "like_count": 0,
          "quote_count": 0,
          "reply_count": 0,
          "retweet_count": 0
        },
        "referenced_tweets": [
          {
            "id": "2048636734435709384",
            "type": "replied_to"
          }
        ],
        "reply_settings": "everyone",
        "text": "@zhouzhouneko2 成分太复杂啦性价比不如白兔，是厚生省认证的日本oder品鉴榜第七位ꉂ(ˊᗜˋ*) https://t.co/x1ECRS8wXp"
      },
      {
        "article": {},
        "attachments": {
          "media_keys": [
            "3_2048636730291671040"
          ]
        },
        "author_id": "1403720942858035201",
        "conversation_id": "2048636734435709384",
        "created_at": "2026-04-27T05:33:53.000Z",
        "edit_controls": {
          "editable_until": "2026-04-27T06:33:53.000Z",
          "edits_remaining": 5,
          "is_edit_eligible": true
        },
        "edit_history_tweet_ids": [
          "2048636734435709384"
        ],
        "entities": {
          "urls": [
            {
              "display_url": "pic.x.com/UeiJeorZnh",
              "end": 36,
              "expanded_url": "https://x.com/zhouzhouneko2/status/2048636734435709384/photo/1",
              "media_key": "3_2048636730291671040",
              "start": 13,
              "url": "https://t.co/UeiJeorZnh"
            }
          ]
        },
        "geo": {},
        "id": "2048636734435709384",
        "lang": "ja",
        "note_tweet": {
          "entities": {}
        },
        "possibly_sensitive": false,
        "public_metrics": {
          "bookmark_count": 0,
          "impression_count": 1133,
          "like_count": 15,
          "quote_count": 0,
          "reply_count": 8,
          "retweet_count": 0
        },
        "reply_settings": "everyone",
        "text": "新ルル能o吗，o过一些些 https://t.co/UeiJeorZnh"
      }
    ],
    "users": [
      {
        "created_at": "2012-01-18T18:17:48.000Z",
        "description": "绝世大坏猫🐈‍⬛咬人也咬自己，咬完再挠一爪子🐾别靠太近，我会咬你也可能抱你。——坏猫不讲理，只会哈气",
        "id": "467659726",
        "location": "距你0.7KM",
        "name": "坏猫",
        "profile_image_url": "https://pbs.twimg.com/profile_images/2046649877283901440/KYxuEqRD_normal.jpg",
        "protected": false,
        "public_metrics": {
          "followers_count": 2774,
          "following_count": 9,
          "like_count": 3643,
          "listed_count": 4,
          "media_count": 198,
          "tweet_count": 843
        },
        "username": "WorstCat",
        "verified": false
      },
      {
        "created_at": "2021-06-12T14:29:19.000Z",
        "description": "转生了\n\n您的赛博猫咪｜双相｜互fo｜mtf｜二次元｜ENFP/INFP｜微键政｜传递爱 希望 自由｜ 方舟 雀魂 肉鸽 博德之门｜闲聊 安慰与抱抱( ´•ω•)ノ｜写作ing｜希望成为温柔的人｜世界破破烂烂，喵喵缝缝补补｜🚪28/58/168/288",
        "id": "1403720942858035201",
        "location": "喵星✨",
        "name": "周周喵🐈",
        "pinned_tweet_id": "1907031259274211613",
        "profile_image_url": "https://pbs.twimg.com/profile_images/1772551411274027008/V0C-jVfn_normal.jpg",
        "protected": false,
        "public_metrics": {
          "followers_count": 2658,
          "following_count": 2198,
          "like_count": 11736,
          "listed_count": 5,
          "media_count": 240,
          "tweet_count": 2378
        },
        "username": "zhouzhouneko2",
        "verified": false
      }
    ]
  }
}