{
  "data": {
    "article": {},
    "attachments": {},
    "author_id": "467659726",
    "conversation_id": "2048807147719602196",
    "created_at": "2026-04-27T18:36:51.000Z",
    "edit_controls": {
      "editable_until": "2026-04-27T19:36:51.000Z",
      "edits_remaining": 5,
      "is_edit_eligible": false
    },
    "edit_history_tweet_ids": [
      "2048833772846710981"
    ],
    "entities": {
      "mentions": [
        {
          "end": 9,
          "id": "2013321876224057344",
          "start": 0,
          "username": "OTxiashu"
        },
        {
          "end": 20,
          "id": "1634944403872833536",
          "start": 10,
          "username": "wmy072011"
        }
      ]
    },
    "geo": {},
    "id": "2048833772846710981",
    "in_reply_to_user_id": "2013321876224057344",
    "lang": "ja",
    "note_tweet": {
      "entities": {}
    },
    "possibly_sensitive": false,
    "public_metrics": {
      "bookmark_count": 0,
      "impression_count": 0,
      "like_count": 0,
      "quote_count": 0,
      "reply_count": 0,
      "retweet_count": 0
    },
    "referenced_tweets": [
      {
        "id": "2048814489890595111",
        "type": "replied_to"
      }
    ],
    "reply_settings": "everyone",
    "text": "@OTxiashu @wmy072011 美工刀用完用酒精擦干净晾干再收回去就好，生锈了就换刀片，修眉刀锈了就不要了(｡･ω･｡)ﾉ♡"
  },
  "includes": {
    "tweets": [
      {
        "article": {},
        "attachments": {},
        "author_id": "467659726",
        "conversation_id": "2048807147719602196",
        "created_at": "2026-04-27T18:36:51.000Z",
        "edit_controls": {
          "editable_until": "2026-04-27T19:36:51.000Z",
          "edits_remaining": 5,
          "is_edit_eligible": false
        },
        "edit_history_tweet_ids": [
          "2048833772846710981"
        ],
        "entities": {
          "mentions": [
            {
              "end": 9,
              "id": "2013321876224057344",
              "start": 0,
              "username": "OTxiashu"
            },
            {
              "end": 20,
              "id": "1634944403872833536",
              "start": 10,
              "username": "wmy072011"
            }
          ]
        },
        "geo": {},
        "id": "2048833772846710981",
        "in_reply_to_user_id": "2013321876224057344",
        "lang": "ja",
        "note_tweet": {
          "entities": {}
        },
        "possibly_sensitive": false,
        "public_metrics": {
          "bookmark_count": 0,
          "impression_count": 0,
          "like_count": 0,
          "quote_count": 0,
          "reply_count": 0,
          "retweet_count": 0
        },
        "referenced_tweets": [
          {
            "id": "2048814489890595111",
            "type": "replied_to"
          }
        ],
        "reply_settings": "everyone",
        "text": "@OTxiashu @wmy072011 美工刀用完用酒精擦干净晾干再收回去就好，生锈了就换刀片，修眉刀锈了就不要了(｡･ω･｡)ﾉ♡"
      },
      {
        "article": {},
        "attachments": {},
        "author_id": "2013321876224057344",
        "conversation_id": "2048807147719602196",
        "created_at": "2026-04-27T17:20:14.000Z",
        "edit_controls": {
          "editable_until": "2026-04-27T18:20:14.000Z",
          "edits_remaining": 5,
          "is_edit_eligible": false
        },
        "edit_history_tweet_ids": [
          "2048814489890595111"
        ],
        "entities": {
          "mentions": [
            {
              "end": 10,
              "id": "1634944403872833536",
              "start": 0,
              "username": "wmy072011"
            }
          ]
        },
        "geo": {},
        "id": "2048814489890595111",
        "in_reply_to_user_id": "1634944403872833536",
        "lang": "zh",
        "note_tweet": {
          "entities": {}
        },
        "possibly_sensitive": false,
        "public_metrics": {
          "bookmark_count": 0,
          "impression_count": 12,
          "like_count": 0,
          "quote_count": 0,
          "reply_count": 1,
          "retweet_count": 0
        },
        "referenced_tweets": [
          {
            "id": "2048808936447595001",
            "type": "replied_to"
          }
        ],
        "reply_settings": "everyone",
        "text": "@wmy072011 呜呜呜呜😭我不割 只是裁剪a4纸 抱抱你"
      }
    ],
    "users": [
      {
        "created_at": "2012-01-18T18:17:48.000Z",
        "description": "绝世大坏猫🐈‍⬛咬人也咬自己，咬完再挠一爪子🐾别靠太近，我会咬你也可能抱你。——坏猫不讲理，只会哈气",
        "id": "467659726",
        "location": "距你0.7KM",
        "name": "坏猫",
        "profile_image_url": "https://pbs.twimg.com/profile_images/2046649877283901440/KYxuEqRD_normal.jpg",
        "protected": false,
        "public_metrics": {
          "followers_count": 2776,
          "following_count": 9,
          "like_count": 3656,
          "listed_count": 4,
          "media_count": 198,
          "tweet_count": 847
        },
        "username": "WorstCat",
        "verified": false
      },
      {
        "created_at": "2026-01-19T18:46:10.000Z",
        "description": "无我梦中",
        "entities": {
          "url": {
            "urls": [
              {
                "display_url": "ngl.link/ot78725",
                "end": 23,
                "expanded_url": "https://ngl.link/ot78725",
                "start": 0,
                "url": "https://t.co/RFlA1XtlG6"
              }
            ]
          }
        },
        "id": "2013321876224057344",
        "location": "沃尔库塔-5",
        "name": "OT夏树",
        "pinned_tweet_id": "2045458839068356985",
        "profile_image_url": "https://pbs.twimg.com/profile_images/2048795940132356096/qEoI3YLY_normal.jpg",
        "protected": false,
        "public_metrics": {
          "followers_count": 575,
          "following_count": 483,
          "like_count": 9390,
          "listed_count": 0,
          "media_count": 265,
          "tweet_count": 3680
        },
        "url": "https://t.co/RFlA1XtlG6",
        "username": "OTxiashu",
        "verified": false
      },
      {
        "created_at": "2023-03-12T15:48:24.000Z",
        "description": "希望明天过的顺利",
        "id": "1634944403872833536",
        "name": "十二点",
        "pinned_tweet_id": "2034682318695407936",
        "profile_image_url": "https://pbs.twimg.com/profile_images/1808798311559929856/zxLxGTxB_normal.jpg",
        "protected": false,
        "public_metrics": {
          "followers_count": 1194,
          "following_count": 337,
          "like_count": 40263,
          "listed_count": 1,
          "media_count": 1388,
          "tweet_count": 13224
        },
        "username": "wmy072011",
        "verified": false
      }
    ]
  }
}